HowdenParser/__init__.py
HowdenParser/parameter/__init__.py
HowdenParser/parameter/llamaparser.py
HowdenParser/parameter/mistralocr.py
HowdenParser/parser.py
HowdenParser/parsers/__init__.py
HowdenParser/parsers/langchain_parser.py
HowdenParser/parsers/llama_parser.py
HowdenParser/parsers/mistral_parser.py
howdenparser-5.2.6.dist-info/METADATA
howdenparser-5.2.6.dist-info/WHEEL
howdenparser-5.2.6.dist-info/RECORD
