Metadata-Version: 2.4
Name: HowdenParser
Version: 5.2.6
Summary: A simple configuration manager with Pydantic and JSON export.
License: MIT
Keywords: config,configuration,pydantic,json
Author: JesperThoftIllemannJ
Author-email: jesper.jaeger@howdendanmark.dk
Requires-Python: >=3.12,<3.14
Classifier: License :: OSI Approved :: MIT License
Classifier: Programming Language :: Python :: 3
Classifier: Programming Language :: Python :: 3.12
Classifier: Programming Language :: Python :: 3.13
Requires-Dist: langchain (>=1.1.3,<2.0.0)
Requires-Dist: llama-parse (>=0.6.58,<0.7.0)
Requires-Dist: mistralai (>=1.9.3,<2.0.0)
Requires-Dist: pdf2image (>=1.17.0,<2.0.0)
Requires-Dist: pypdf2 (>=3.0.1,<4.0.0)
Requires-Dist: pytest (>=9.0.2,<10.0.0)
Requires-Dist: tomli-w (>=1.2.0,<2.0.0)
